<?xml version="1.0" encoding="UTF-8"?>
<SlimOTA xmlns:xsi="http://www.w3.org/2001/XMLSchema-instance" xsi:noNamespaceSchemaLocation="ota.xsd">
    <Stable>
        <lettuce>
            <Filename>RR-N-v5.8.4-20170812-lettuce-Official.zip</Filename>
            <RomUrl
                id="rom"
                title="Rom"
                description="Download latest ResurrectionRemix build">https://sourceforge.net/projects/resurrectionremix/files/lettuce/RR-N-v5.8.4-20170812-lettuce-Official.zip/download</RomUrl>
            <ChangelogUrl
                id="changelog"
                title="Changelog"
                description="View Changelog">https://github.com/ResurrectionRemix/android_vendor_resurrection/blob/nougat/CHANGELOG.mkdn</ChangelogUrl>
            <OpenGappsUrl
                id="open_gapps"
                title="OpenGApps"
                description="Download latest OpenGApps">http://opengapps.org</OpenGappsUrl>
            <BeansGappsUrl
            	id="beans_gapps"
            	title="Beans Dynamic GApps"
            	description="Download Beans latest GApps">https://www.androidfilehost.com/?fid=889764386195918677</BeansGappsUrl>
	</lettuce>
    </Stable>
</SlimOTA>
